{
  "memo_max_days": 30,
  "allowed_sectors": ["crypto", "finance", "economy"],
  "sector_map": {
    "crypto": [
      "crypto",
      "bitcoin",
      "ethereum",
      "defi",
      "layer-1",
      "layer-2",
      "stablecoins",
      "altcoins",
      "solana",
      "base",
      "l1",
      "l2",
      "airdrop",
      "meme",
      "btc",
      "eth",
      "sol",
      "staking",
      "restaking",
      "liquid-staking",
      "eigenlayer",
      "lido",
      "perps",
      "derivatives",
      "dex",
      "lending",
      "borrowing",
      "bridges",
      "cross-chain",
      "oracles",
      "zk",
      "rollups",
      "nft",
      "gaming",
      "depin"
    ],
    "finance": [
      "stocks",
      "equities",
      "earnings",
      "rates",
      "fed",
      "treasury",
      "banking",
      "commodities",
      "bonds",
      "etf",
      "oil",
      "gold"
    ],
    "economy": [
      "inflation",
      "cpi",
      "gdp",
      "jobs",
      "unemployment",
      "ppi",
      "pmi",
      "macroeconomy",
      "recession",
      "growth"
    ]
  },
  "exclude_tags": ["politics", "election", "geopolitics", "government"],
  "ref_percentile": 0.9,
  "weights": {
    "resolutionIntegrity": 30,
    "liquidityMicrostructure": 25,
    "modelability": 20,
    "participationQuality": 15,
    "strategicFit": 10
  },
  "penalties": {
    "restricted": -10,
    "missing_tags": -5
  },
  "flags_thresholds": {
    "min_liquidity": 5000,
    "min_volume24h": 10000,
    "min_open_interest": 5000
  },
  "score_version": "v2",
  "sync_market_limit": 500,
  "sync_batch_size": 25
}
